djangoldp_digest/__init__.py
djangoldp_digest/apps.py
djangoldp_digest/settings.py
djangoldp_digest/management/__init__.py
djangoldp_digest/management/commands/__init__.py
djangoldp_digest/management/commands/digest.py
djangoldp_digest/templates/__init__.py
djangoldp_digest/templates/digest/circle.html
djangoldp_digest/templates/digest/circles.html
djangoldp_digest/templates/digest/event.html
djangoldp_digest/templates/digest/events.html
djangoldp_digest/templates/digest/inbox.html
djangoldp_digest/templates/digest/inbox_mentions.html
djangoldp_digest/templates/digest/inbox_messages.html
djangoldp_digest/templates/digest/poll.html
djangoldp_digest/templates/digest/polls.html
djangoldp_digest/templates/digest/resource.html
djangoldp_digest/templates/digest/resources.html
djangoldp_digest/templates/digest/template.html
djangoldp_digest/templates/digest/vote.html
djangoldp_digest/templates/digest/votes.html
djangoldp_digest/templates/digest/votes_heading.html
djangoldp_digest-1.0.36.dist-info/METADATA
djangoldp_digest-1.0.36.dist-info/WHEEL
djangoldp_digest-1.0.36.dist-info/top_level.txt
djangoldp_digest-1.0.36.dist-info/RECORD
